{
  "project_info": {
    "project_number": "912707879045",
    "firebase_url": "https://diabeton-8d0de-default-rtdb.europe-west1.firebasedatabase.app",
    "project_id": "diabeton-8d0de",
    "storage_bucket": "diabeton-8d0de.appspot.com"
  },
  "client": [
    {
      "client_info": {
        "mobilesdk_app_id": "1:912707879045:android:b6776219f7b318bf4129ec",
        "android_client_info": {
          "package_name": "com.Company.Diabeton_2"
        }
      },
      "oauth_client": [
        {
          "client_id": "912707879045-363nsl9l13vsr9tn6jsfu8tmltb7eqce.apps.googleusercontent.com",
          "client_type": 3
        }
      ],
      "api_key": [
        {
          "current_key": "AIzaSyA50JA5V6tXwtQ4Tde4J4rm0wkIZ7CD7v0"
        }
      ],
      "services": {
        "appinvite_service": {
          "other_platform_oauth_client": [
            {
              "client_id": "912707879045-363nsl9l13vsr9tn6jsfu8tmltb7eqce.apps.googleusercontent.com",
              "client_type": 3
            }
          ]
        }
      }
    },
    {
      "client_info": {
        "mobilesdk_app_id": "1:912707879045:android:5d2021a51b30410b4129ec",
        "android_client_info": {
          "package_name": "com.DefaultCompany.Diabeton_2"
        }
      },
      "oauth_client": [
        {
          "client_id": "912707879045-363nsl9l13vsr9tn6jsfu8tmltb7eqce.apps.googleusercontent.com",
          "client_type": 3
        }
      ],
      "api_key": [
        {
          "current_key": "AIzaSyA50JA5V6tXwtQ4Tde4J4rm0wkIZ7CD7v0"
        }
      ],
      "services": {
        "appinvite_service": {
          "other_platform_oauth_client": [
            {
              "client_id": "912707879045-363nsl9l13vsr9tn6jsfu8tmltb7eqce.apps.googleusercontent.com",
              "client_type": 3
            }
          ]
        }
      }
    }
  ],
  "configuration_version": "1"
}